comiq/__init__.py
comiq/ai_processing.py
comiq/comiq.py
comiq/models.py
comiq/ocr.py
comiq/prompts.py
comiq/utils.py
comiq-0.1.3.dist-info/licenses/LICENSE
comiq-0.1.3.dist-info/METADATA
comiq-0.1.3.dist-info/WHEEL
comiq-0.1.3.dist-info/top_level.txt
comiq-0.1.3.dist-info/RECORD
