Metadata-Version: 2.4
Name: comiq
Version: 0.1.3
Summary: Comic-Focused Hybrid OCR Python Library
Author-email: MoltenSteel <stonesteel27@gmail.com>
Project-URL: Homepage, https://github.com/StoneSteel27/ComiQ
Project-URL: Bug Tracker, https://github.com/StoneSteel27/ComiQ/issues
Classifier: Programming Language :: Python :: 3
Classifier: License :: OSI Approved :: MIT License
Classifier: Operating System :: OS Independent
Requires-Python: >=3.10
License-File: LICENSE
Requires-Dist: openai
Requires-Dist: python-dotenv
Requires-Dist: pydantic
Requires-Dist: easyocr
Requires-Dist: paddleocr<3.0
Requires-Dist: paddlepaddle<3.0
Dynamic: license-file
